find_run_diff/__init__.py
find_run_diff/_modidx.py
find_run_diff/core.py
find_run_diff-0.0.4.dist-info/LICENSE
find_run_diff-0.0.4.dist-info/METADATA
find_run_diff-0.0.4.dist-info/WHEEL
find_run_diff-0.0.4.dist-info/entry_points.txt
find_run_diff-0.0.4.dist-info/top_level.txt
find_run_diff-0.0.4.dist-info/RECORD
