Metadata-Version: 2.1
Name: find-run-diff
Version: 0.0.4
Summary: Checks two directories for subdirectories with minor name variations, the find the subdirectories which appear to be missing in the targer directory.
Home-page: https://github.com/kimleeng/find_run_diff/
Author: Kim Ng
Author-email: kimleeng@gmail.com
License: Apache Software License 2.0
Keywords: nbdev
Classifier: Development Status :: 3 - Alpha
Classifier: Intended Audience :: Developers
Classifier: Natural Language :: English
Classifier: Programming Language :: Python :: 3.7
Classifier: Programming Language :: Python :: 3.8
Classifier: Programming Language :: Python :: 3.9
Classifier: Programming Language :: Python :: 3.10
Classifier: License :: OSI Approved :: Apache Software License
Requires-Python: >=3.7
License-File: LICENSE
Requires-Dist: python-dotenv
Provides-Extra: dev
